installcmd/__init__.py
installcmd/cli.py
installcmd/commands.yaml
installcmd/lib.py
installcmd/linux.py
installcmd/mac.py
installcmd-0.4.7.dist-info/METADATA
installcmd-0.4.7.dist-info/WHEEL
installcmd-0.4.7.dist-info/entry_points.txt
installcmd-0.4.7.dist-info/top_level.txt
installcmd-0.4.7.dist-info/RECORD
