Metadata-Version: 2.1
Name: installcmd
Version: 0.4.7
Summary: Print correct command for installing a package.
Home-page: https://github.com/metov/installcmd
Author: Azat Akhmetov
Classifier: Programming Language :: Python :: 3
Classifier: Operating System :: OS Independent
Requires-Python: >=3.6
Requires-Dist: coloredlogs
Requires-Dist: docopt
Requires-Dist: metovlogs
Requires-Dist: python-dotenv
Requires-Dist: pyyaml
